tacofunniest/__init__.py
tacofunniest/lib2.py
tacofunniest-1.0.dist-info/METADATA
tacofunniest-1.0.dist-info/WHEEL
tacofunniest-1.0.dist-info/top_level.txt
tacofunniest-1.0.dist-info/RECORD
