Metadata-Version: 2.1
Name: tacofunniest
Version: 1.0
Summary: Taiwan No. 1
Home-page: http://github.com/storborg/tacofunniest
Author: Taco Ann
Author-email: asdfg59420@gmail.com
License: MIT
Platform: UNKNOWN
